adviceslip/__init__.py
adviceslip/__main__.py
adviceslip/cli.py
adviceslip/client.py
adviceslip/exceptions.py
adviceslip/objects.py
adviceslip-1.1.0.dist-info/entry_points.txt
adviceslip-1.1.0.dist-info/WHEEL
adviceslip-1.1.0.dist-info/METADATA
adviceslip-1.1.0.dist-info/RECORD
